dagster_ibis_duckdb/__init__.py
dagster_ibis_duckdb/client.py
dagster_ibis_duckdb/io_manager.py
dagster_ibis_duckdb/type_handler.py
dagster_ibis_duckdb-0.1.6.dist-info/METADATA
dagster_ibis_duckdb-0.1.6.dist-info/WHEEL
dagster_ibis_duckdb-0.1.6.dist-info/RECORD
